<?xml version="1.0" encoding="utf-8" ?>
<dwsync>
<file name="Fitment.ts" server="39.97.127.220" local="132295466680000000" remote="132316981200000000" Dst="0" />
<file name="GridRow.ts" server="39.97.127.220" local="132295466680000000" remote="132316981200000000" Dst="0" />
<file name="DetailsList.ts" server="39.97.127.220" local="132295466680000000" remote="132316981200000000" Dst="0" />
<file name="TableGrid.ts" server="39.97.127.220" local="132295466680000000" remote="132316981200000000" Dst="0" />
<file name="TableMerge.ts" server="39.97.127.220" local="132295466680000000" remote="132316981200000000" Dst="0" />
<file name="RunOperation.ts" server="39.97.127.220" local="132295466680000000" remote="132316981200000000" Dst="0" />
<file name="Transitions.ts" server="39.97.127.220" local="132295466680000000" remote="132316981200000000" Dst="0" />
<file name="Warehouse.ts" server="39.97.127.220" local="132295466680000000" remote="132316981200000000" Dst="0" />
</dwsync>